physoce/__init__.py
physoce/graph.py
physoce/io.py
physoce/oceans.py
physoce/stats.py
physoce/tseries.py
physoce/util.py
physoce-0.0.2.dist-info/LICENSE.md
physoce-0.0.2.dist-info/METADATA
physoce-0.0.2.dist-info/WHEEL
physoce-0.0.2.dist-info/top_level.txt
physoce-0.0.2.dist-info/RECORD
