Metadata-Version: 2.1
Name: physoce
Version: 0.0.2
Summary: Python tools for Physical Oceanography
Home-page: https://github.com/physoce/physoce-py
Author: Tom Connolly
Author-email: tconnolly@mlml.calstate.edu
License: UNKNOWN
Platform: UNKNOWN
